workflow_manager
