Metadata-Version: 1.1
Name: workflow-manager
Version: 0.3
Summary: Wizard-link workflow manager
Home-page: http://github.com/dimtruck/workflow-manager-py
Author: Dimitry Ushakov
Author-email: me@dimitryushakov.com
License: MIT
Platform: UNKNOWN
Classifier: Development Status :: 3 - Alpha
Classifier: License :: OSI Approved :: MIT License
Classifier: Programming Language :: Python :: 3 :: Only
Classifier: Topic :: Software Development :: Libraries
